CHANGES.txt
CONTRIBUTORS.txt
MANIFEST.in
README.txt
setup.cfg
setup.py
Products/__init__.py
Products.mediaPage.egg-info/PKG-INFO
Products.mediaPage.egg-info/SOURCES.txt
Products.mediaPage.egg-info/dependency_links.txt
Products.mediaPage.egg-info/entry_points.txt
Products.mediaPage.egg-info/namespace_packages.txt
Products.mediaPage.egg-info/not-zip-safe
Products.mediaPage.egg-info/paster_plugins.txt
Products.mediaPage.egg-info/requires.txt
Products.mediaPage.egg-info/top_level.txt
Products/mediaPage/README.txt
Products/mediaPage/__init__.py
Products/mediaPage/config.py
Products/mediaPage/configure.zcml
Products/mediaPage/browser/__init__.py
Products/mediaPage/browser/configure.zcml
Products/mediaPage/content/__init__.py
Products/mediaPage/content/configure.zcml
Products/mediaPage/content/mediapage.py
Products/mediaPage/interfaces/__init__.py
Products/mediaPage/interfaces/mediapage.py
Products/mediaPage/portlets/__init__.py
Products/mediaPage/portlets/configure.zcml
Products/mediaPage/profiles/default/factorytool.xml
Products/mediaPage/profiles/default/metadata.xml
Products/mediaPage/profiles/default/portlets.xml
Products/mediaPage/profiles/default/rolemap.xml
Products/mediaPage/profiles/default/types.xml
Products/mediaPage/profiles/default/types/MediaPage.xml
Products/mediaPage/profiles/default/types/Page.xml
Products/mediaPage/tests/__init__.py
Products/mediaPage/tests/base.py
Products/mediaPage/tests/test_doctest.py
docs/HISTORY.txt
docs/INSTALL.txt
docs/LICENSE.GPL
docs/LICENSE.txt