Metadata-Version: 1.0
Name: Products.mediaPage
Version: 0.5
Summary: Folderish Page
Home-page: http://svn.plone.org/svn/collective/
Author: David Jonas
Author-email: david@itsnotthatkind.org
License: GPL
Keywords: plone type page folderish
Platform: UNKNOWN
Classifier: Framework :: Plone
Classifier: Intended Audience :: Developers
Classifier: License :: OSI Approved :: GNU General Public License (GPL)
